{
	"name": "Iterative_pipeline",
	"properties": {
		"activities": [
			{
				"name": "ForEach",
				"type": "ForEach",
				"dependsOn": [],
				"userProperties": [],
				"typeProperties": {
					"items": {
						"value": "@createArray('Product','Customer','CustomerAddress')",
						"type": "Expression"
					},
					"activities": [
						{
							"name": "Copy data for multiple tables",
							"type": "Copy",
							"dependsOn": [],
							"policy": {
								"timeout": "0.12:00:00",
								"retry": 0,
								"retryIntervalInSeconds": 30,
								"secureOutput": false,
								"secureInput": false
							},
							"userProperties": [],
							"typeProperties": {
								"source": {
									"type": "AzureSqlSource",
									"queryTimeout": "02:00:00",
									"partitionOption": "None"
								},
								"sink": {
									"type": "DelimitedTextSink",
									"storeSettings": {
										"type": "AzureBlobFSWriteSettings"
									},
									"formatSettings": {
										"type": "DelimitedTextWriteSettings",
										"quoteAllText": true,
										"fileExtension": ".txt"
									}
								},
								"enableStaging": false,
								"translator": {
									"type": "TabularTranslator",
									"typeConversion": true,
									"typeConversionSettings": {
										"allowDataTruncation": true,
										"treatBooleanAsNumber": false
									}
								}
							},
							"inputs": [
								{
									"referenceName": "SQL_Generic_DS",
									"type": "DatasetReference",
									"parameters": {
										"schemaName": "saleslt",
										"tableName": {
											"value": "@item()",
											"type": "Expression"
										}
									}
								}
							],
							"outputs": [
								{
									"referenceName": "CSV_Generic_DS",
									"type": "DatasetReference",
									"parameters": {
										"directoryPath": {
											"value": "@item()",
											"type": "Expression"
										}
									}
								}
							]
						}
					]
				}
			}
		],
		"annotations": [],
		"lastPublishTime": "2023-07-25T05:26:49Z"
	},
	"type": "Microsoft.DataFactory/factories/pipelines"
}