{
	"$schema": "http://schema.management.azure.com/schemas/2015-01-01/deploymentTemplate.json#",
	"contentVersion": "1.0.0.0",
	"parameters": {
		"factoryName": {
			"type": "string",
			"metadata": "Data Factory name",
			"defaultValue": "TanujitADF"
		}
	},
	"variables": {
		"factoryId": "[concat('Microsoft.DataFactory/factories/', parameters('factoryName'))]"
	},
	"resources": [
		{
			"name": "[concat(parameters('factoryName'), '/GetMetaData_Folder_Pipeline')]",
			"type": "Microsoft.DataFactory/factories/pipelines",
			"apiVersion": "2018-06-01",
			"properties": {
				"activities": [
					{
						"name": "Get Metadata1",
						"type": "GetMetadata",
						"dependsOn": [],
						"policy": {
							"timeout": "0.12:00:00",
							"retry": 0,
							"retryIntervalInSeconds": 30,
							"secureOutput": false,
							"secureInput": false
						},
						"userProperties": [],
						"typeProperties": {
							"dataset": {
								"referenceName": "CSV_Product_DS",
								"type": "DatasetReference",
								"parameters": {}
							},
							"fieldList": [
								"childItems"
							],
							"storeSettings": {
								"type": "AzureBlobFSReadSettings",
								"recursive": true,
								"enablePartitionDiscovery": false
							},
							"formatSettings": {
								"type": "DelimitedTextReadSettings"
							}
						}
					}
				],
				"policy": {
					"elapsedTimeMetric": {},
					"cancelAfter": {}
				},
				"annotations": []
			},
			"dependsOn": []
		},
		{
			"name": "[concat(parameters('factoryName'), '/GetMetaData_Pipeline_File')]",
			"type": "Microsoft.DataFactory/factories/pipelines",
			"apiVersion": "2018-06-01",
			"properties": {
				"activities": [
					{
						"name": "Get Metadata1",
						"type": "GetMetadata",
						"dependsOn": [],
						"policy": {
							"timeout": "0.12:00:00",
							"retry": 0,
							"retryIntervalInSeconds": 30,
							"secureOutput": false,
							"secureInput": false
						},
						"userProperties": [],
						"typeProperties": {
							"dataset": {
								"referenceName": "SQL_Generic_DS",
								"type": "DatasetReference",
								"parameters": {
									"schemaName": "saleslt",
									"tableName": "customer"
								}
							},
							"fieldList": [
								"structure"
							]
						}
					}
				],
				"policy": {
					"elapsedTimeMetric": {},
					"cancelAfter": {}
				},
				"annotations": []
			},
			"dependsOn": []
		},
		{
			"name": "[concat(parameters('factoryName'), '/Ingest_SQL_to_CSV_Generic')]",
			"type": "Microsoft.DataFactory/factories/pipelines",
			"apiVersion": "2018-06-01",
			"properties": {
				"activities": [
					{
						"name": "SQL_to_CSV_Parameterized",
						"type": "Copy",
						"dependsOn": [],
						"policy": {
							"timeout": "0.12:00:00",
							"retry": 0,
							"retryIntervalInSeconds": 30,
							"secureOutput": false,
							"secureInput": false
						},
						"userProperties": [],
						"typeProperties": {
							"source": {
								"type": "AzureSqlSource",
								"queryTimeout": "02:00:00",
								"partitionOption": "None"
							},
							"sink": {
								"type": "DelimitedTextSink",
								"storeSettings": {
									"type": "AzureBlobFSWriteSettings"
								},
								"formatSettings": {
									"type": "DelimitedTextWriteSettings",
									"quoteAllText": true,
									"fileExtension": ".txt"
								}
							},
							"enableStaging": false,
							"translator": {
								"type": "TabularTranslator",
								"typeConversion": true,
								"typeConversionSettings": {
									"allowDataTruncation": true,
									"treatBooleanAsNumber": false
								}
							}
						},
						"inputs": [
							{
								"referenceName": "SQL_Generic_DS",
								"type": "DatasetReference",
								"parameters": {
									"schemaName": "SalesLT",
									"tableName": "CustomerAddress"
								}
							}
						],
						"outputs": [
							{
								"referenceName": "CSV_Generic_DS",
								"type": "DatasetReference",
								"parameters": {
									"directoryPath": "Address",
									"fileName": "Customer Address"
								}
							}
						]
					}
				],
				"policy": {
					"elapsedTimeMetric": {},
					"cancelAfter": {}
				},
				"annotations": [],
				"lastPublishTime": "2023-07-24T08:51:05Z"
			},
			"dependsOn": []
		},
		{
			"name": "[concat(parameters('factoryName'), '/Iterative_pipeline')]",
			"type": "Microsoft.DataFactory/factories/pipelines",
			"apiVersion": "2018-06-01",
			"properties": {
				"activities": [
					{
						"name": "ForEach",
						"type": "ForEach",
						"dependsOn": [],
						"userProperties": [],
						"typeProperties": {
							"items": {
								"value": "@createArray('Product','Customer','CustomerAddress')",
								"type": "Expression"
							},
							"activities": [
								{
									"name": "Copy data for multiple tables",
									"type": "Copy",
									"dependsOn": [],
									"policy": {
										"timeout": "0.12:00:00",
										"retry": 0,
										"retryIntervalInSeconds": 30,
										"secureOutput": false,
										"secureInput": false
									},
									"userProperties": [],
									"typeProperties": {
										"source": {
											"type": "AzureSqlSource",
											"queryTimeout": "02:00:00",
											"partitionOption": "None"
										},
										"sink": {
											"type": "DelimitedTextSink",
											"storeSettings": {
												"type": "AzureBlobFSWriteSettings"
											},
											"formatSettings": {
												"type": "DelimitedTextWriteSettings",
												"quoteAllText": true,
												"fileExtension": ".txt"
											}
										},
										"enableStaging": false,
										"translator": {
											"type": "TabularTranslator",
											"typeConversion": true,
											"typeConversionSettings": {
												"allowDataTruncation": true,
												"treatBooleanAsNumber": false
											}
										}
									},
									"inputs": [
										{
											"referenceName": "SQL_Generic_DS",
											"type": "DatasetReference",
											"parameters": {
												"schemaName": "saleslt",
												"tableName": {
													"value": "@item()",
													"type": "Expression"
												}
											}
										}
									],
									"outputs": [
										{
											"referenceName": "CSV_Generic_DS",
											"type": "DatasetReference",
											"parameters": {
												"directoryPath": {
													"value": "@item()",
													"type": "Expression"
												},
												"fileName": {
													"value": "@item()",
													"type": "Expression"
												}
											}
										}
									]
								}
							]
						}
					}
				],
				"policy": {
					"elapsedTimeMetric": {},
					"cancelAfter": {}
				},
				"annotations": [],
				"lastPublishTime": "2023-07-25T05:26:49Z"
			},
			"dependsOn": []
		},
		{
			"name": "[concat(parameters('factoryName'), '/Join_tables_SQL_query')]",
			"type": "Microsoft.DataFactory/factories/pipelines",
			"apiVersion": "2018-06-01",
			"properties": {
				"activities": [
					{
						"name": "Copy data1",
						"type": "Copy",
						"dependsOn": [],
						"policy": {
							"timeout": "0.12:00:00",
							"retry": 0,
							"retryIntervalInSeconds": 30,
							"secureOutput": false,
							"secureInput": false
						},
						"userProperties": [],
						"typeProperties": {
							"source": {
								"type": "AzureSqlSource",
								"sqlReaderQuery": "select c.customerid, c.firstname, c.lastname, ca.addressid, ca.addresstype from saleslt.customer c join saleslt.customeraddress ca on c.customerid = ca.customerid",
								"queryTimeout": "02:00:00",
								"partitionOption": "None"
							},
							"sink": {
								"type": "DelimitedTextSink",
								"storeSettings": {
									"type": "AzureBlobFSWriteSettings"
								},
								"formatSettings": {
									"type": "DelimitedTextWriteSettings",
									"quoteAllText": true,
									"fileExtension": ".txt"
								}
							},
							"enableStaging": false,
							"translator": {
								"type": "TabularTranslator",
								"typeConversion": true,
								"typeConversionSettings": {
									"allowDataTruncation": true,
									"treatBooleanAsNumber": false
								}
							}
						},
						"inputs": [
							{
								"referenceName": "SQL_DB_DS",
								"type": "DatasetReference",
								"parameters": {}
							}
						],
						"outputs": [
							{
								"referenceName": "CSV_Generic_DS",
								"type": "DatasetReference",
								"parameters": {
									"directoryPath": "Customer_Full_Data",
									"fileName": "Customer_Full_Data"
								}
							}
						]
					}
				],
				"policy": {
					"elapsedTimeMetric": {},
					"cancelAfter": {}
				},
				"annotations": [],
				"lastPublishTime": "2023-07-25T06:08:46Z"
			},
			"dependsOn": []
		},
		{
			"name": "[concat(parameters('factoryName'), '/Join_tables_SQL_query_concat_column')]",
			"type": "Microsoft.DataFactory/factories/pipelines",
			"apiVersion": "2018-06-01",
			"properties": {
				"activities": [
					{
						"name": "Copy data-Concat",
						"type": "Copy",
						"dependsOn": [],
						"policy": {
							"timeout": "0.12:00:00",
							"retry": 0,
							"retryIntervalInSeconds": 30,
							"secureOutput": false,
							"secureInput": false
						},
						"userProperties": [],
						"typeProperties": {
							"source": {
								"type": "AzureSqlSource",
								"sqlReaderQuery": "select c.customerid, c.firstname + ' ' + c.lastname as full_name, ca.addressid, ca.addresstype from saleslt.customer c join saleslt.customeraddress ca on c.customerid = ca.customerid",
								"queryTimeout": "02:00:00",
								"partitionOption": "None"
							},
							"sink": {
								"type": "DelimitedTextSink",
								"storeSettings": {
									"type": "AzureBlobFSWriteSettings"
								},
								"formatSettings": {
									"type": "DelimitedTextWriteSettings",
									"quoteAllText": true,
									"fileExtension": ".txt"
								}
							},
							"enableStaging": false,
							"translator": {
								"type": "TabularTranslator",
								"typeConversion": true,
								"typeConversionSettings": {
									"allowDataTruncation": true,
									"treatBooleanAsNumber": false
								}
							}
						},
						"inputs": [
							{
								"referenceName": "SQL_DB_DS",
								"type": "DatasetReference",
								"parameters": {}
							}
						],
						"outputs": [
							{
								"referenceName": "CSV_Generic_DS",
								"type": "DatasetReference",
								"parameters": {
									"directoryPath": "Customer_Full_Data",
									"fileName": "Concat-Customer-Details"
								}
							}
						]
					}
				],
				"policy": {
					"elapsedTimeMetric": {},
					"cancelAfter": {}
				},
				"annotations": [],
				"lastPublishTime": "2023-07-25T06:08:46Z"
			},
			"dependsOn": []
		},
		{
			"name": "[concat(parameters('factoryName'), '/Lookup-If-Else')]",
			"type": "Microsoft.DataFactory/factories/pipelines",
			"apiVersion": "2018-06-01",
			"properties": {
				"description": "Create a pipeline name 'Ingestion_Product_To_JSON' which will copy all the product records as JSON only if total number of records >10.",
				"activities": [
					{
						"name": "Lookup1",
						"type": "Lookup",
						"dependsOn": [],
						"policy": {
							"timeout": "0.12:00:00",
							"retry": 0,
							"retryIntervalInSeconds": 30,
							"secureOutput": false,
							"secureInput": false
						},
						"userProperties": [],
						"typeProperties": {
							"source": {
								"type": "AzureSqlSource",
								"sqlReaderQuery": "select count(*) as RecordCount from saleslt.product",
								"queryTimeout": "02:00:00",
								"partitionOption": "None"
							},
							"dataset": {
								"referenceName": "SQL_DB_Product_DS",
								"type": "DatasetReference",
								"parameters": {}
							}
						}
					},
					{
						"name": "If Condition",
						"type": "IfCondition",
						"dependsOn": [
							{
								"activity": "Lookup1",
								"dependencyConditions": [
									"Succeeded"
								]
							}
						],
						"userProperties": [],
						"typeProperties": {
							"expression": {
								"value": "@greater(activity('Lookup1').output.firstRow.RecordCount,10)",
								"type": "Expression"
							},
							"ifTrueActivities": [
								{
									"name": "Copy data1",
									"type": "Copy",
									"dependsOn": [],
									"policy": {
										"timeout": "0.12:00:00",
										"retry": 0,
										"retryIntervalInSeconds": 30,
										"secureOutput": false,
										"secureInput": false
									},
									"userProperties": [],
									"typeProperties": {
										"source": {
											"type": "AzureSqlSource",
											"queryTimeout": "02:00:00",
											"partitionOption": "None"
										},
										"sink": {
											"type": "JsonSink",
											"storeSettings": {
												"type": "AzureBlobFSWriteSettings"
											},
											"formatSettings": {
												"type": "JsonWriteSettings"
											}
										},
										"enableStaging": false
									},
									"inputs": [
										{
											"referenceName": "SQL_DB_Product_DS",
											"type": "DatasetReference",
											"parameters": {}
										}
									],
									"outputs": [
										{
											"referenceName": "JSON_Generic_DS",
											"type": "DatasetReference",
											"parameters": {
												"directoryPath": "Lookup_If_Else",
												"fileName": "Products"
											}
										}
									]
								}
							]
						}
					}
				],
				"policy": {
					"elapsedTimeMetric": {},
					"cancelAfter": {}
				},
				"annotations": []
			},
			"dependsOn": []
		},
		{
			"name": "[concat(parameters('factoryName'), '/SFTP_Pipeline')]",
			"type": "Microsoft.DataFactory/factories/pipelines",
			"apiVersion": "2018-06-01",
			"properties": {
				"activities": [
					{
						"name": "Copy data1",
						"type": "Copy",
						"dependsOn": [],
						"policy": {
							"timeout": "0.12:00:00",
							"retry": 0,
							"retryIntervalInSeconds": 30,
							"secureOutput": false,
							"secureInput": false
						},
						"userProperties": [],
						"typeProperties": {
							"source": {
								"type": "BinarySource",
								"storeSettings": {
									"type": "SftpReadSettings",
									"recursive": true,
									"disableChunking": false
								},
								"formatSettings": {
									"type": "BinaryReadSettings"
								}
							},
							"sink": {
								"type": "BinarySink",
								"storeSettings": {
									"type": "AzureBlobFSWriteSettings"
								}
							},
							"enableStaging": false
						},
						"inputs": [
							{
								"referenceName": "SFTP_Binary_DS",
								"type": "DatasetReference",
								"parameters": {}
							}
						],
						"outputs": [
							{
								"referenceName": "SFTP_ADLS",
								"type": "DatasetReference",
								"parameters": {}
							}
						]
					}
				],
				"policy": {
					"elapsedTimeMetric": {},
					"cancelAfter": {}
				},
				"annotations": []
			},
			"dependsOn": []
		},
		{
			"name": "[concat(parameters('factoryName'), '/Child_Pipeline_Lookup_If_Else')]",
			"type": "Microsoft.DataFactory/factories/pipelines",
			"apiVersion": "2018-06-01",
			"properties": {
				"description": "Create a pipeline name 'Ingestion_Product_Addres_To_JSON' which will copy all the product records as JSON only if total number of records >10. After that check total record count in address table if they are greater than 100 then copy the adress table data as CSV in ADLS.",
				"activities": [
					{
						"name": "Execute Pipeline",
						"type": "ExecutePipeline",
						"dependsOn": [],
						"userProperties": [],
						"typeProperties": {
							"pipeline": {
								"referenceName": "Lookup-If-Else",
								"type": "PipelineReference"
							},
							"waitOnCompletion": true,
							"parameters": {}
						}
					},
					{
						"name": "Lookup1",
						"type": "Lookup",
						"dependsOn": [
							{
								"activity": "Execute Pipeline",
								"dependencyConditions": [
									"Completed"
								]
							}
						],
						"policy": {
							"timeout": "0.12:00:00",
							"retry": 0,
							"retryIntervalInSeconds": 30,
							"secureOutput": false,
							"secureInput": false
						},
						"userProperties": [],
						"typeProperties": {
							"source": {
								"type": "AzureSqlSource",
								"sqlReaderQuery": "select count(*) as TotalCount from saleslt.address",
								"queryTimeout": "02:00:00",
								"partitionOption": "None"
							},
							"dataset": {
								"referenceName": "SQL_Generic_DS",
								"type": "DatasetReference",
								"parameters": {
									"schemaName": "saleslt",
									"tableName": "address"
								}
							}
						}
					},
					{
						"name": "If Condition1",
						"type": "IfCondition",
						"dependsOn": [
							{
								"activity": "Lookup1",
								"dependencyConditions": [
									"Succeeded"
								]
							}
						],
						"userProperties": [],
						"typeProperties": {
							"expression": {
								"value": "@greater(activity('Lookup1').output.firstRow.TotalCount, 100)",
								"type": "Expression"
							},
							"ifTrueActivities": [
								{
									"name": "Copy data1",
									"type": "Copy",
									"dependsOn": [],
									"policy": {
										"timeout": "0.12:00:00",
										"retry": 0,
										"retryIntervalInSeconds": 30,
										"secureOutput": false,
										"secureInput": false
									},
									"userProperties": [],
									"typeProperties": {
										"source": {
											"type": "AzureSqlSource",
											"queryTimeout": "02:00:00",
											"partitionOption": "None"
										},
										"sink": {
											"type": "DelimitedTextSink",
											"storeSettings": {
												"type": "AzureBlobFSWriteSettings"
											},
											"formatSettings": {
												"type": "DelimitedTextWriteSettings",
												"quoteAllText": true,
												"fileExtension": ".txt"
											}
										},
										"enableStaging": false,
										"translator": {
											"type": "TabularTranslator",
											"typeConversion": true,
											"typeConversionSettings": {
												"allowDataTruncation": true,
												"treatBooleanAsNumber": false
											}
										}
									},
									"inputs": [
										{
											"referenceName": "SQL_Generic_DS",
											"type": "DatasetReference",
											"parameters": {
												"schemaName": "saleslt",
												"tableName": "address"
											}
										}
									],
									"outputs": [
										{
											"referenceName": "CSV_Generic_DS",
											"type": "DatasetReference",
											"parameters": {
												"directoryPath": "Address_Lookup",
												"fileName": "Address"
											}
										}
									]
								}
							]
						}
					}
				],
				"policy": {
					"elapsedTimeMetric": {},
					"cancelAfter": {}
				},
				"annotations": []
			},
			"dependsOn": [
				"[concat(variables('factoryId'), '/pipelines/Lookup-If-Else')]"
			]
		}
	]
}